AUTHORS.rst
CONTRIBUTING.rst
HISTORY.rst
LICENSE
MANIFEST.in
README.rst
setup.cfg
setup.py
django_helpscout/__init__.py
django_helpscout/helpers.py
django_helpscout/models.py
django_helpscout/settings.py
django_helpscout/urls.py
django_helpscout/views.py
django_helpscout.egg-info/PKG-INFO
django_helpscout.egg-info/SOURCES.txt
django_helpscout.egg-info/dependency_links.txt
django_helpscout.egg-info/not-zip-safe
django_helpscout.egg-info/requires.txt
django_helpscout.egg-info/top_level.txt
django_helpscout/templates/django_helpscout/404.html
django_helpscout/templates/django_helpscout/helpscout.html