Metadata-Version: 1.1
Name: django-helpscout
Version: 0.6.2
Summary: Help Scout integration for Django
Home-page: https://github.com/victorneo/Django-Helpscout
Author: Victor Neo
Author-email: icyisamu@gmail.com
License: Apache License V2
Keywords: Django-Helpscout,Django,Help Scout
Platform: UNKNOWN
Classifier: Development Status :: 4 - Beta
Classifier: Framework :: Django
Classifier: Intended Audience :: Developers
Classifier: License :: OSI Approved :: Apache Software License
Classifier: Natural Language :: English
Classifier: Programming Language :: Python :: 2
Classifier: Programming Language :: Python :: 2.6
Classifier: Programming Language :: Python :: 2.7
Classifier: Programming Language :: Python :: 3.4
